ngo/__init__.py
ngo/__main__.py
ngo/api.py
ngo/cleanup.py
ngo/dependency.py
ngo/inline.py
ngo/literal_duplication.py
ngo/math_simplification.py
ngo/minmax_aggregates.py
ngo/normalize.py
ngo/projection.py
ngo/py.typed
ngo/sum_aggregates.py
ngo/symmetry.py
ngo/unused.py
ngo/utils/__init__.py
ngo/utils/ast.py
ngo/utils/globals.py
ngo/utils/parser.py
ngo-1.0.2.dist-info/LICENSE
ngo-1.0.2.dist-info/METADATA
ngo-1.0.2.dist-info/WHEEL
ngo-1.0.2.dist-info/entry_points.txt
ngo-1.0.2.dist-info/top_level.txt
ngo-1.0.2.dist-info/RECORD
