Metadata-Version: 2.1
Name: ngo
Version: 1.0.2
Summary: Optimizes non ground logic programs.
Author-email: Max Ostrowski <max.ostrowski@potassco.com>
License: MIT License
Project-URL: Homepage, https://potassco.org/ngo
Project-URL: Documentation, https://potassco.org/ngo
Project-URL: Repository, http://github.com/potassco/ngo
Requires-Python: >=3.11
License-File: LICENSE
Requires-Dist: clingo <6.0,>=5.7.1
Requires-Dist: networkx >=3.1
Requires-Dist: sympy >=1.12
Provides-Extra: dev
Requires-Dist: ngo[doc,format,lint,test,typecheck] ; extra == 'dev'
Requires-Dist: pre-commit ; extra == 'dev'
Provides-Extra: doc
Requires-Dist: pdoc ; extra == 'doc'
Provides-Extra: format
Requires-Dist: black ; extra == 'format'
Requires-Dist: isort ; extra == 'format'
Provides-Extra: lint
Requires-Dist: pylint ; extra == 'lint'
Requires-Dist: ngo[test] ; extra == 'lint'
Provides-Extra: test
Requires-Dist: pytest ; extra == 'test'
Requires-Dist: coverage ; extra == 'test'
Provides-Extra: typecheck
Requires-Dist: types-setuptools ; extra == 'typecheck'
Requires-Dist: mypy ; extra == 'typecheck'
Requires-Dist: networkx-stubs ; extra == 'typecheck'
Requires-Dist: ngo[test] ; extra == 'typecheck'
